5_semester/FPGA/lab_4/src/frequency_divider.v
module frequency_divider(
    input wire clock_in,
    input wire [4:0] n,
    output wire clock_out,
    output reg [4:0] counter
);

initial begin
    counter = 5'b00000;
end

reg clock_out_flag = 1'b0;
assign clock_out = clock_out_flag;

always @(clock_in) begin
    counter = counter + 1;
    if (counter == n) begin
        counter <= 5'b00000;
        clock_out_flag <= ~clock_out_flag;
    end
end
endmodule

5_semester/FPGA/lab_2/src/frequency_divider_testbench.v
`timescale 1ns/1ps

module frequency_divider_testbench();
reg clock_in;
reg [4:0] n;
integer step;
wire clock_out;
wire [4:0] counter;

frequency_divider fd(
    .clock_in(clock_in),
    .n(n),
    .clock_out(clock_out),
    .counter(counter)
);

initial begin
    $dumpfile("frequency_divider_dump.vcd");
    $dumpvars(0, frequency_divider_testbench);
    $monitor("%d|clock_in=%b|clock_out=%b|counter=%d|", step, clock_in, clock_out, counter);

    step = 0;
    clock_in = 1'b0;
    n = 5'b11010;

    #181
    $finish;
end

// Генератор тактовых импульсов
always begin
    #2  
    step <= step + 1;
    clock_in <= ~clock_in;
    
end
endmodule

5_semester/FPGA/lab_2/src/frequency_divider_dump.vcd
$date
	Thu Oct 12 10:33:32 2023
$end
$version
	Icarus Verilog
$end
$timescale
	1ps
$end
$scope module frequency_divider_testbench $end
$var wire 5 ! counter [4:0] $end
$var wire 1 " clock_out $end
$var reg 1 # clock_in $end
$var reg 5 $ n [4:0] $end
$var integer 32 % step [31:0] $end
$scope module fd $end
$var wire 1 # clock_in $end
$var wire 1 " clock_out $end
$var wire 5 & n [4:0] $end
$var reg 1 ' clock_out_flag $end
$var reg 5 ( counter [4:0] $end
$upscope $end
$upscope $end
$enddefinitions $end
$comment Show the parameter values. $end
$dumpall
$end
#0
$dumpvars
b1 (
0'
b11010 &
b0 %
b11010 $
0#
0"
b1 !
$end
#2000
b10 !
b10 (
1#
b1 %
#4000
b11 !
b11 (
0#
b10 %
#6000
b100 !
b100 (
1#
b11 %
#8000
b101 !
b101 (
0#
b100 %
#10000
b110 !
b110 (
1#
b101 %
#12000
b111 !
b111 (
0#
b110 %
#14000
b1000 !
b1000 (
1#
b111 %
#16000
b1001 !
b1001 (
0#
b1000 %
#18000
b1010 !
b1010 (
1#
b1001 %
#20000
b1011 !
b1011 (
0#
b1010 %
#22000
b1100 !
b1100 (
1#
b1011 %
#24000
b1101 !
b1101 (
0#
b1100 %
#26000
b1110 !
b1110 (
1#
b1101 %
#28000
b1111 !
b1111 (
0#
b1110 %
#30000
b10000 !
b10000 (
1#
b1111 %
#32000
b10001 !
b10001 (
0#
b10000 %
#34000
b10010 !
b10010 (
1#
b10001 %
#36000
b10011 !
b10011 (
0#
b10010 %
#38000
b10100 !
b10100 (
1#
b10011 %
#40000
b10101 !
b10101 (
0#
b10100 %
#42000
b10110 !
b10110 (
1#
b10101 %
#44000
b10111 !
b10111 (
0#
b10110 %
#46000
b11000 !
b11000 (
1#
b10111 %
#48000
b11001 !
b11001 (
0#
b11000 %
#50000
1"
1'
b0 !
b0 (
1#
b11001 %
#52000
b1 !
b1 (
0#
b11010 %
#54000
b10 !
b10 (
1#
b11011 %
#56000
b11 !
b11 (
0#
b11100 %
#58000
b100 !
b100 (
1#
b11101 %
#60000
b101 !
b101 (
0#
b11110 %
#62000
b110 !
b110 (
1#
b11111 %
#64000
b111 !
b111 (
0#
b100000 %
#66000
b1000 !
b1000 (
1#
b100001 %
#68000
b1001 !
b1001 (
0#
b100010 %
#70000
b1010 !
b1010 (
1#
b100011 %
#72000
b1011 !
b1011 (
0#
b100100 %
#74000
b1100 !
b1100 (
1#
b100101 %
#76000
b1101 !
b1101 (
0#
b100110 %
#78000
b1110 !
b1110 (
1#
b100111 %
#80000
b1111 !
b1111 (
0#
b101000 %
#82000
b10000 !
b10000 (
1#
b101001 %
#84000
b10001 !
b10001 (
0#
b101010 %
#86000
b10010 !
b10010 (
1#
b101011 %
#88000
b10011 !
b10011 (
0#
b101100 %
#90000
b10100 !
b10100 (
1#
b101101 %
#92000
b10101 !
b10101 (
0#
b101110 %
#94000
b10110 !
b10110 (
1#
b101111 %
#96000
b10111 !
b10111 (
0#
b110000 %
#98000
b11000 !
b11000 (
1#
b110001 %
#100000
b11001 !
b11001 (
0#
b110010 %
#102000
0"
0'
b0 !
b0 (
1#
b110011 %
#104000
b1 !
b1 (
0#
b110100 %
#106000
b10 !
b10 (
1#
b110101 %
#108000
b11 !
b11 (
0#
b110110 %
#110000
b100 !
b100 (
1#
b110111 %
#112000
b101 !
b101 (
0#
b111000 %
#114000
b110 !
b110 (
1#
b111001 %
#116000
b111 !
b111 (
0#
b111010 %
#118000
b1000 !
b1000 (
1#
b111011 %
#120000
b1001 !
b1001 (
0#
b111100 %
#122000
b1010 !
b1010 (
1#
b111101 %
#124000
b1011 !
b1011 (
0#
b111110 %
#126000
b1100 !
b1100 (
1#
b111111 %
#128000
b1101 !
b1101 (
0#
b1000000 %
#130000
b1110 !
b1110 (
1#
b1000001 %
#132000
b1111 !
b1111 (
0#
b1000010 %
#134000
b10000 !
b10000 (
1#
b1000011 %
#136000
b10001 !
b10001 (
0#
b1000100 %
#138000
b10010 !
b10010 (
1#
b1000101 %
#140000
b10011 !
b10011 (
0#
b1000110 %
#142000
b10100 !
b10100 (
1#
b1000111 %
#144000
b10101 !
b10101 (
0#
b1001000 %
#146000
b10110 !
b10110 (
1#
b1001001 %
#148000
b10111 !
b10111 (
0#
b1001010 %
#150000
b11000 !
b11000 (
1#
b1001011 %
#152000
b11001 !
b11001 (
0#
b1001100 %
#154000
1"
1'
b0 !
b0 (
1#
b1001101 %
#156000
b1 !
b1 (
0#
b1001110 %
#158000
b10 !
b10 (
1#
b1001111 %
#160000
b11 !
b11 (
0#
b1010000 %
#162000
b100 !
b100 (
1#
b1010001 %
#164000
b101 !
b101 (
0#
b1010010 %
#166000
b110 !
b110 (
1#
b1010011 %
#168000
b111 !
b111 (
0#
b1010100 %
#170000
b1000 !
b1000 (
1#
b1010101 %
#172000
b1001 !
b1001 (
0#
b1010110 %
#174000
b1010 !
b1010 (
1#
b1010111 %
#176000
b1011 !
b1011 (
0#
b1011000 %
#178000
b1100 !
b1100 (
1#
b1011001 %
#180000
b1101 !
b1101 (
0#
b1011010 %
