5_semester/FPGA/lab_4/src/uart_states.vh
// Состояния UART

`define RESET           3'b001  // сброс
`define IDLE            3'b010  // индикатор не активного передатчика
`define START           3'b011  // начало передачи
`define TRANSMITTING    3'b100  // передаются данные
`define STOP            3'b101  // конец передачи

5_semester/FPGA/lab_4/src/uart_transmitter.v
// 8-bit UART Transmitter.
// Able to transmit 8 bits of serial data, one start bit, one stop bit.
// When transmit is complete {done} is driven high for one clock cycle.
// When transmit is in progress {busy} is driven high.
// Clock should be decreased to baud rate.
`include "uart_states.vh"
`define SENTENCE_LEN 11


module uart_transmitter(
    input  wire       clk,      // baud rate
    input  wire       enable,   // enable signal
    input  wire       start,    // start of transaction
    input  wire [7:0] in,       // data to transmit
    output reg        out,      // tx
    output reg        done,     // end on transaction
    output reg        busy      // transaction is in process
);
    /*wire [7:0] in;
    reg [7:0] sentence [0:`SENTENCE_LEN-1];
    sentence[0] = 8'h68;    // 'h68 - код символа 'h' в шестнадцатеричной системе
    sentence[1] = 8'h65;    // 'h65 - код символа 'e' в шестнадцатеричной системе
    sentence[2] = 8'h6C;    // 'h6C - код символа 'l' в шестнадцатеричной системе
    sentence[3] = 8'h6C;    // 'h6C - код символа 'l' в шестнадцатеричной системе
    sentence[4] = 8'h6F;    // 'h6F - код символа 'o' в шестнадцатеричной системе
    sentence[5] = 8'h20;    // 'h20 - код символа пробела в шестнадцатеричной системе
    sentence[6] = 8'h77;    // 'h77 - код символа 'w' в шестнадцатеричной системе
    sentence[7] = 8'h6F;    // 'h6F - код символа 'o' в шестнадцатеричной системе
    sentence[8] = 8'h72;    // 'h72 - код символа 'r' в шестнадцатеричной системе
    sentence[9] = 8'h6C;    // 'h6C - код символа 'l' в шестнадцатеричной системе
    sentence[10] = 8'h64;   // 'h64 - код символа 'd' в шестнадцатеричной системе
    integer i = 1;*/
    
    reg  [2:0] state  = `IDLE;
    reg  [7:0] data   = 8'b0;    // to store a copy of input data
    reg  [2:0] bitIdx = 3'b0;    // for 8-bit data
    wire [2:0] idx;
    
    assign idx = bitIdx;

    always @(posedge clk) begin
        case (state)
            //`RESET      : begin
            //    state   <= `IDLE;
            //end
            `IDLE       : begin
                out     <= 1'b1;        // drive line high for idle
                done    <= 1'b0;
                busy    <= 1'b0;
                bitIdx  <= 3'b0;
                data    <= 8'b0;
                if (start & enable) begin
                    data    <= in;      // save a copy of input data
                    state   <= `START;  // start transmitting
                end
            end
            `START       : begin
                out      <= 1'b0;       // send start bit (low)
                busy     <= 1'b1;
                state    <= `TRANSMITTING;
            end
            `TRANSMITTING: begin        // Wait 8 clock cycles for data bits to be sent
                out     <= data[idx];
                if (&bitIdx) begin
                    bitIdx  <= 3'b0;
                    state   <= `STOP;
                end else begin
                    bitIdx  <= bitIdx + 1'b1;
                end
            end
            `STOP       : begin         // Send out Stop bit (high)
                done    <= 1'b1;
                data    <= 8'b0;
                state   <= `IDLE;
            end
        endcase
    end
    /*
    always @(posedge done) begin
        in = sentence[i];
        i = i + 1;
        if (i > 12) begin
            
        end
    end
    */
endmodule

5_semester/FPGA/lab_4/src/uart_receiver.v
// 8-bit UART Receiver.
// Able to receive 8 bits of serial data, one start bit, one stop bit.
// When receive is complete {done} is driven high for one clock cycle.
// Output data should be taken away by a few clocks or can be lost.
// When receive is in progress {busy} is driven high.
// Clock should be decreased to baud rate.
`include "uart_states.vh"


module uart_receiver(
    input  wire       clk,      // baud rate
    input  wire       enable,   // enable signal
    input  wire       in,       // rx
    output reg  [7:0] out,      // received data
    output reg        done,     // end on transaction
    output reg        busy,     // transaction is in process
    output reg        err       // error while receiving data
);

    reg [2:0] state = `IDLE;
    reg [2:0] bitIdx = 3'b0;        // for 8-bit data
    //reg [1:0] inputSw = 2'b0;       // shift reg for input signal state
    //reg [3:0] clockCount = 4'b0;    // count clocks for 16x oversample
    reg [7:0] receivedData = 8'b0;  // temporary storage for input data

    initial begin
        out <= 8'b0;
        err <= 1'b0;
        done <= 1'b0;
        busy <= 1'b0;
    end

    always @(posedge clk) begin
        //inputSw = { inputSw[0], in };

        //if (!enable) begin
        //    state = `IDLE;
        //end

        case (state)
            /*`RESET:     begin
                out <= 8'b0;
                err <= 1'b0;
                done <= 1'b0;
                busy <= 1'b0;
                bitIdx <= 3'b0;
                //clockCount <= 4'b0;
                receivedData <= 8'b0;
                if (enable) begin
                    state <= `IDLE;
                end
            end*/

            `IDLE: begin
                done <= 1'b0;
                out <= 8'b0;
                bitIdx <= 3'b0;  
                receivedData <= 8'b0;
                busy <= 1'b1;
                err <= 1'b0;
                //if (&clockCount) begin
                //clockCount <= 4'b0;   
                if (~in) begin   
                    state <= `TRANSMITTING;
                end
                
                //end else if (!(&inputSw) || |clockCount) begin
                    // Check bit to make sure it's still low
                    //if (&inputSw) begin
                       // err <= 1'b1;
                       // state <= `RESET;
                    //end
                    //clockCount <= clockCount + 4'b1;
                //end
            end

            // Wait 8 full cycles to receive serial data
            `TRANSMITTING: begin
                //if (&clockCount) begin  // save one bit of received data
                    //clockCount <= 4'b0;
                    // TODO: check the most popular value
                    receivedData[bitIdx] <= in;//inputSw[0];
                    if (&bitIdx) begin
                        bitIdx <= 3'b0;
                        state <= `STOP;
                    end else begin
                        bitIdx <= bitIdx + 3'b1;
                    end
                //end else begin
                   // clockCount <= clockCount + 4'b1;
                //end
            end

            /*
            * Baud clock may not be running at exactly the same rate as the
            * transmitter. Next start bit is allowed on at least half of stop bit.
            */
            `STOP: begin
                //if (&bitIdx || &clockCount || (clockCount >= 4'h8 && !(|inputSw))) begin
                    state <= `IDLE;
                    done <= 1'b1;
                    busy <= 1'b0;
                    out <= receivedData;//[0];
                    //clockCount <= 4'b0;
                //end else begin
                    //clockCount <= clockCount + 1;
                    // Check bit to make sure it's still high
                    //if (!(|inputSw)) begin
                        //err <= 1'b1;
                        //state <= `RESET;
                    //end
                //end
            end

            //default: state <= `IDLE;
        endcase
    end

endmodule;

5_semester/FPGA/lab_4/src/uart.v
// Simple 8-bit UART realization.
// Combine receiver, transmitter and baud rate generator.
// Able to operate 8 bits of serial data, one start bit, one stop bit.


module uart  #(
    parameter CLOCK_RATE = 100000000, // board internal clock
    parameter BAUD_RATE = 9600
)(
    input wire clk,

    // rx interface
    input wire rx,
    input wire rxEn,
    output wire [7:0] out,
    output wire rxDone,
    output wire rxBusy,
    output wire rxErr,

    // tx interface
    output wire tx,
    input wire txEn,
    input wire txStart,
    input wire [7:0] in,
    output wire txDone,
    output wire txBusy
);
    wire rxClk;
    wire txClk;
    assign rxClk = clk;
    assign txClk = clk;
    /*
    baud_rate_generator #(
        .CLOCK_RATE(CLOCK_RATE),
        .BAUD_RATE(BAUD_RATE)
    ) generatorInst (
        .clk(clk),
        .rxClk(rxClk),
        .txClk(txClk)
    );*/
 
    uart_receiver urx (
        .clk(rxClk),
        .enable(rxEn),
        .in(rx),
        .out(out),
        .done(rxDone),
        .busy(rxBusy),
        .err(rxErr)
    );

    uart_transmitter utx (
        .clk(txClk),
        .enable(txEn),
        .start(txStart),
        .in(in),
        .out(tx),
        .done(txDone),
        .busy(txBusy)
    );

endmodule

5_semester/FPGA/lab_4/src/uart_testbench.v
`timescale 1 ns / 100 ps
`define SENTENCE_LEN 11

module uart_tb();
    reg clk = 0;
    // rx interface
    reg rxEn = 1;
    wire [7:0] out;
    wire rxDone;
    wire rxBusy;
    wire rxErr;

    // tx interface
    reg txEn = 1;
    reg txStart = 1;
    reg [7:0] in;
    wire txDone;
    wire txBusy;
    
    wire tx_rx_pipe;
    reg [7:0] sentence [0:`SENTENCE_LEN-1];

    uart u (
        .clk(clk),
        .rx(tx_rx_pipe),
        .rxEn(rxEn),
        .out(out),
        .rxDone(rxDone),
        .rxBusy(rxBusy),
        .rxErr(rxErr),
        .tx(tx_rx_pipe),
        .txEn(txEn),
        .txStart(txStart),
        .in(in),
        .txDone(txDone),
        .txBusy(txBusy)
    );

    // simulation init
    initial begin 
        sentence[0] = 8'h68;    // 'h68 - код символа 'h' в шестнадцатеричной системе
        sentence[1] = 8'h65;    // 'h65 - код символа 'e' в шестнадцатеричной системе
        sentence[2] = 8'h6C;    // 'h6C - код символа 'l' в шестнадцатеричной системе
        sentence[3] = 8'h6C;    // 'h6C - код символа 'l' в шестнадцатеричной системе
        sentence[4] = 8'h6F;    // 'h6F - код символа 'o' в шестнадцатеричной системе
        sentence[5] = 8'h20;    // 'h20 - код символа пробела в шестнадцатеричной системе
        sentence[6] = 8'h77;    // 'h77 - код символа 'w' в шестнадцатеричной системе
        sentence[7] = 8'h6F;    // 'h6F - код символа 'o' в шестнадцатеричной системе
        sentence[8] = 8'h72;    // 'h72 - код символа 'r' в шестнадцатеричной системе
        sentence[9] = 8'h6C;    // 'h6C - код символа 'l' в шестнадцатеричной системе
        sentence[10] = 8'h64;   // 'h64 - код символа 'd' в шестнадцатеричной системе
        in = sentence[0];
        $dumpfile("uart_dump.vcd");
        $dumpvars(0, uart_tb);
        $monitor("%d %c", out, out);  
    end
    
    integer i = 1;
    always @(posedge txDone) begin
        in = sentence[i];
        i = i + 1;
        if (i > 12) begin
            $finish();
        end
    end
    
    // clock generator
    always begin
        #1 clk = ~clk;
    end

endmodule

5_semester/FPGA/lab_4/src/uart_dump.vcd
$date
	Thu Dec 14 16:09:31 2023
$end
$version
	Icarus Verilog
$end
$timescale
	100ps
$end
$scope module uart_tb $end
$var wire 1 ! tx_rx_pipe $end
$var wire 1 " txDone $end
$var wire 1 # txBusy $end
$var wire 1 $ rxErr $end
$var wire 1 % rxDone $end
$var wire 1 & rxBusy $end
$var wire 8 ' out [7:0] $end
$var reg 1 ( clk $end
$var reg 8 ) in [7:0] $end
$var reg 1 * rxEn $end
$var reg 1 + txEn $end
$var reg 1 , txStart $end
$var integer 32 - i [31:0] $end
$scope module u $end
$var wire 1 ( clk $end
$var wire 8 . in [7:0] $end
$var wire 1 / rxClk $end
$var wire 1 * rxEn $end
$var wire 1 0 txClk $end
$var wire 1 + txEn $end
$var wire 1 , txStart $end
$var wire 1 " txDone $end
$var wire 1 # txBusy $end
$var wire 1 ! tx $end
$var wire 1 $ rxErr $end
$var wire 1 % rxDone $end
$var wire 1 & rxBusy $end
$var wire 1 ! rx $end
$var wire 8 1 out [7:0] $end
$var parameter 32 2 BAUD_RATE $end
$var parameter 32 3 CLOCK_RATE $end
$scope module urx $end
$var wire 1 / clk $end
$var wire 1 * enable $end
$var wire 1 ! in $end
$var reg 3 4 bitIdx [2:0] $end
$var reg 1 & busy $end
$var reg 1 % done $end
$var reg 1 $ err $end
$var reg 8 5 out [7:0] $end
$var reg 8 6 receivedData [7:0] $end
$var reg 3 7 state [2:0] $end
$upscope $end
$scope module utx $end
$var wire 1 0 clk $end
$var wire 1 + enable $end
$var wire 3 8 idx [2:0] $end
$var wire 8 9 in [7:0] $end
$var wire 1 , start $end
$var reg 3 : bitIdx [2:0] $end
$var reg 1 # busy $end
$var reg 8 ; data [7:0] $end
$var reg 1 " done $end
$var reg 1 ! out $end
$var reg 3 < state [2:0] $end
$upscope $end
$upscope $end
$upscope $end
$enddefinitions $end
$comment Show the parameter values. $end
$dumpall
b101111101011110000100000000 3
b10010110000000 2
$end
#0
$dumpvars
b10 <
b0 ;
b0 :
b1101000 9
b0 8
b10 7
b0 6
b0 5
b0 4
b0 1
00
0/
b1101000 .
b1 -
1,
1+
1*
b1101000 )
0(
b0 '
0&
0%
0$
x#
x"
x!
$end
#10
1&
b11 <
b1101000 ;
0#
0"
1!
1/
10
1(
#20
0/
00
0(
#30
b100 <
1#
0!
1/
10
1(
#40
0/
00
0(
#50
b100 7
b1 8
b1 :
1/
10
1(
#60
0/
00
0(
#70
b1 4
b10 8
b10 :
1/
10
1(
#80
0/
00
0(
#90
b10 4
b11 8
b11 :
1/
10
1(
#100
0/
00
0(
#110
b11 4
b100 8
b100 :
1!
1/
10
1(
#120
0/
00
0(
#130
b100 4
b1000 6
b101 8
b101 :
0!
1/
10
1(
#140
0/
00
0(
#150
b101 4
b110 8
b110 :
1!
1/
10
1(
#160
0/
00
0(
#170
b110 4
b101000 6
b111 8
b111 :
1/
10
1(
#180
0/
00
0(
#190
b111 4
b1101000 6
b101 <
b0 8
b0 :
0!
1/
10
1(
#200
0/
00
0(
#210
b10 -
b1100101 )
b1100101 .
b1100101 9
b101 7
b0 4
b10 <
b0 ;
1"
1/
10
1(
#220
0/
00
0(
#230
b1101000 '
b1101000 1
b1101000 5
0&
1%
b10 7
b11 <
b1100101 ;
0#
0"
1!
1/
10
1(
#240
0/
00
0(
#250
1&
b0 6
b0 '
b0 1
b0 5
0%
b100 <
1#
0!
1/
10
1(
#260
0/
00
0(
#270
b100 7
b1 8
b1 :
1!
1/
10
1(
#280
0/
00
0(
#290
b1 4
b1 6
b10 8
b10 :
0!
1/
10
1(
#300
0/
00
0(
#310
b10 4
b11 8
b11 :
1!
1/
10
1(
#320
0/
00
0(
#330
b11 4
b101 6
b100 8
b100 :
0!
1/
10
1(
#340
0/
00
0(
#350
b100 4
b101 8
b101 :
1/
10
1(
#360
0/
00
0(
#370
b101 4
b110 8
b110 :
1!
1/
10
1(
#380
0/
00
0(
#390
b110 4
b100101 6
b111 8
b111 :
1/
10
1(
#400
0/
00
0(
#410
b111 4
b1100101 6
b101 <
b0 8
b0 :
0!
1/
10
1(
#420
0/
00
0(
#430
b11 -
b1101100 )
b1101100 .
b1101100 9
b101 7
b0 4
b10 <
b0 ;
1"
1/
10
1(
#440
0/
00
0(
#450
b1100101 '
b1100101 1
b1100101 5
0&
1%
b10 7
b11 <
b1101100 ;
0#
0"
1!
1/
10
1(
#460
0/
00
0(
#470
1&
b0 6
b0 '
b0 1
b0 5
0%
b100 <
1#
0!
1/
10
1(
#480
0/
00
0(
#490
b100 7
b1 8
b1 :
1/
10
1(
#500
0/
00
0(
#510
b1 4
b10 8
b10 :
1/
10
1(
#520
0/
00
0(
#530
b10 4
b11 8
b11 :
1!
1/
10
1(
#540
0/
00
0(
#550
b11 4
b100 6
b100 8
b100 :
1/
10
1(
#560
0/
00
0(
#570
b100 4
b1100 6
b101 8
b101 :
0!
1/
10
1(
#580
0/
00
0(
#590
b101 4
b110 8
b110 :
1!
1/
10
1(
#600
0/
00
0(
#610
b110 4
b101100 6
b111 8
b111 :
1/
10
1(
#620
0/
00
0(
#630
b111 4
b1101100 6
b101 <
b0 8
b0 :
0!
1/
10
1(
#640
0/
00
0(
#650
b100 -
b101 7
b0 4
b10 <
b0 ;
1"
1/
10
1(
#660
0/
00
0(
#670
b1101100 '
b1101100 1
b1101100 5
0&
1%
b10 7
b11 <
b1101100 ;
0#
0"
1!
1/
10
1(
#680
0/
00
0(
#690
1&
b0 6
b0 '
b0 1
b0 5
0%
b100 <
1#
0!
1/
10
1(
#700
0/
00
0(
#710
b100 7
b1 8
b1 :
1/
10
1(
#720
0/
00
0(
#730
b1 4
b10 8
b10 :
1/
10
1(
#740
0/
00
0(
#750
b10 4
b11 8
b11 :
1!
1/
10
1(
#760
0/
00
0(
#770
b11 4
b100 6
b100 8
b100 :
1/
10
1(
#780
0/
00
0(
#790
b100 4
b1100 6
b101 8
b101 :
0!
1/
10
1(
#800
0/
00
0(
#810
b101 4
b110 8
b110 :
1!
1/
10
1(
#820
0/
00
0(
#830
b110 4
b101100 6
b111 8
b111 :
1/
10
1(
#840
0/
00
0(
#850
b111 4
b1101100 6
b101 <
b0 8
b0 :
0!
1/
10
1(
#860
0/
00
0(
#870
b101 -
b1101111 )
b1101111 .
b1101111 9
b101 7
b0 4
b10 <
b0 ;
1"
1/
10
1(
#880
0/
00
0(
#890
b1101100 '
b1101100 1
b1101100 5
0&
1%
b10 7
b11 <
b1101111 ;
0#
0"
1!
1/
10
1(
#900
0/
00
0(
#910
1&
b0 6
b0 '
b0 1
b0 5
0%
b100 <
1#
0!
1/
10
1(
#920
0/
00
0(
#930
b100 7
b1 8
b1 :
1!
1/
10
1(
#940
0/
00
0(
#950
b1 4
b1 6
b10 8
b10 :
1/
10
1(
#960
0/
00
0(
#970
b10 4
b11 6
b11 8
b11 :
1/
10
1(
#980
0/
00
0(
#990
b11 4
b111 6
b100 8
b100 :
1/
10
1(
#1000
0/
00
0(
#1010
b100 4
b1111 6
b101 8
b101 :
0!
1/
10
1(
#1020
0/
00
0(
#1030
b101 4
b110 8
b110 :
1!
1/
10
1(
#1040
0/
00
0(
#1050
b110 4
b101111 6
b111 8
b111 :
1/
10
1(
#1060
0/
00
0(
#1070
b111 4
b1101111 6
b101 <
b0 8
b0 :
0!
1/
10
1(
#1080
0/
00
0(
#1090
b110 -
b100000 )
b100000 .
b100000 9
b101 7
b0 4
b10 <
b0 ;
1"
1/
10
1(
#1100
0/
00
0(
#1110
b1101111 '
b1101111 1
b1101111 5
0&
1%
b10 7
b11 <
b100000 ;
0#
0"
1!
1/
10
1(
#1120
0/
00
0(
#1130
1&
b0 6
b0 '
b0 1
b0 5
0%
b100 <
1#
0!
1/
10
1(
#1140
0/
00
0(
#1150
b100 7
b1 8
b1 :
1/
10
1(
#1160
0/
00
0(
#1170
b1 4
b10 8
b10 :
1/
10
1(
#1180
0/
00
0(
#1190
b10 4
b11 8
b11 :
1/
10
1(
#1200
0/
00
0(
#1210
b11 4
b100 8
b100 :
1/
10
1(
#1220
0/
00
0(
#1230
b100 4
b101 8
b101 :
1/
10
1(
#1240
0/
00
0(
#1250
b101 4
b110 8
b110 :
1!
1/
10
1(
#1260
0/
00
0(
#1270
b110 4
b100000 6
b111 8
b111 :
0!
1/
10
1(
#1280
0/
00
0(
#1290
b111 4
b101 <
b0 8
b0 :
1/
10
1(
#1300
0/
00
0(
#1310
b111 -
b1110111 )
b1110111 .
b1110111 9
b101 7
b0 4
b10 <
b0 ;
1"
1/
10
1(
#1320
0/
00
0(
#1330
b100000 '
b100000 1
b100000 5
0&
1%
b10 7
b11 <
b1110111 ;
0#
0"
1!
1/
10
1(
#1340
0/
00
0(
#1350
1&
b0 6
b0 '
b0 1
b0 5
0%
b100 <
1#
0!
1/
10
1(
#1360
0/
00
0(
#1370
b100 7
b1 8
b1 :
1!
1/
10
1(
#1380
0/
00
0(
#1390
b1 4
b1 6
b10 8
b10 :
1/
10
1(
#1400
0/
00
0(
#1410
b10 4
b11 6
b11 8
b11 :
1/
10
1(
#1420
0/
00
0(
#1430
b11 4
b111 6
b100 8
b100 :
0!
1/
10
1(
#1440
0/
00
0(
#1450
b100 4
b101 8
b101 :
1!
1/
10
1(
#1460
0/
00
0(
#1470
b101 4
b10111 6
b110 8
b110 :
1/
10
1(
#1480
0/
00
0(
#1490
b110 4
b110111 6
b111 8
b111 :
1/
10
1(
#1500
0/
00
0(
#1510
b111 4
b1110111 6
b101 <
b0 8
b0 :
0!
1/
10
1(
#1520
0/
00
0(
#1530
b1000 -
b1101111 )
b1101111 .
b1101111 9
b101 7
b0 4
b10 <
b0 ;
1"
1/
10
1(
#1540
0/
00
0(
#1550
b1110111 '
b1110111 1
b1110111 5
0&
1%
b10 7
b11 <
b1101111 ;
0#
0"
1!
1/
10
1(
#1560
0/
00
0(
#1570
1&
b0 6
b0 '
b0 1
b0 5
0%
b100 <
1#
0!
1/
10
1(
#1580
0/
00
0(
#1590
b100 7
b1 8
b1 :
1!
1/
10
1(
#1600
0/
00
0(
#1610
b1 4
b1 6
b10 8
b10 :
1/
10
1(
#1620
0/
00
0(
#1630
b10 4
b11 6
b11 8
b11 :
1/
10
1(
#1640
0/
00
0(
#1650
b11 4
b111 6
b100 8
b100 :
1/
10
1(
#1660
0/
00
0(
#1670
b100 4
b1111 6
b101 8
b101 :
0!
1/
10
1(
#1680
0/
00
0(
#1690
b101 4
b110 8
b110 :
1!
1/
10
1(
#1700
0/
00
0(
#1710
b110 4
b101111 6
b111 8
b111 :
1/
10
1(
#1720
0/
00
0(
#1730
b111 4
b1101111 6
b101 <
b0 8
b0 :
0!
1/
10
1(
#1740
0/
00
0(
#1750
b1001 -
b1110010 )
b1110010 .
b1110010 9
b101 7
b0 4
b10 <
b0 ;
1"
1/
10
1(
#1760
0/
00
0(
#1770
b1101111 '
b1101111 1
b1101111 5
0&
1%
b10 7
b11 <
b1110010 ;
0#
0"
1!
1/
10
1(
#1780
0/
00
0(
#1790
1&
b0 6
b0 '
b0 1
b0 5
0%
b100 <
1#
0!
1/
10
1(
#1800
0/
00
0(
#1810
b100 7
b1 8
b1 :
1/
10
1(
#1820
0/
00
0(
#1830
b1 4
b10 8
b10 :
1!
1/
10
1(
#1840
0/
00
0(
#1850
b10 4
b10 6
b11 8
b11 :
0!
1/
10
1(
#1860
0/
00
0(
#1870
b11 4
b100 8
b100 :
1/
10
1(
#1880
0/
00
0(
#1890
b100 4
b101 8
b101 :
1!
1/
10
1(
#1900
0/
00
0(
#1910
b101 4
b10010 6
b110 8
b110 :
1/
10
1(
#1920
0/
00
0(
#1930
b110 4
b110010 6
b111 8
b111 :
1/
10
1(
#1940
0/
00
0(
#1950
b111 4
b1110010 6
b101 <
b0 8
b0 :
0!
1/
10
1(
#1960
0/
00
0(
#1970
b1010 -
b1101100 )
b1101100 .
b1101100 9
b101 7
b0 4
b10 <
b0 ;
1"
1/
10
1(
#1980
0/
00
0(
#1990
b1110010 '
b1110010 1
b1110010 5
0&
1%
b10 7
b11 <
b1101100 ;
0#
0"
1!
1/
10
1(
#2000
0/
00
0(
#2010
1&
b0 6
b0 '
b0 1
b0 5
0%
b100 <
1#
0!
1/
10
1(
#2020
0/
00
0(
#2030
b100 7
b1 8
b1 :
1/
10
1(
#2040
0/
00
0(
#2050
b1 4
b10 8
b10 :
1/
10
1(
#2060
0/
00
0(
#2070
b10 4
b11 8
b11 :
1!
1/
10
1(
#2080
0/
00
0(
#2090
b11 4
b100 6
b100 8
b100 :
1/
10
1(
#2100
0/
00
0(
#2110
b100 4
b1100 6
b101 8
b101 :
0!
1/
10
1(
#2120
0/
00
0(
#2130
b101 4
b110 8
b110 :
1!
1/
10
1(
#2140
0/
00
0(
#2150
b110 4
b101100 6
b111 8
b111 :
1/
10
1(
#2160
0/
00
0(
#2170
b111 4
b1101100 6
b101 <
b0 8
b0 :
0!
1/
10
1(
#2180
0/
00
0(
#2190
b1011 -
b1100100 )
b1100100 .
b1100100 9
b101 7
b0 4
b10 <
b0 ;
1"
1/
10
1(
#2200
0/
00
0(
#2210
b1101100 '
b1101100 1
b1101100 5
0&
1%
b10 7
b11 <
b1100100 ;
0#
0"
1!
1/
10
1(
#2220
0/
00
0(
#2230
1&
b0 6
b0 '
b0 1
b0 5
0%
b100 <
1#
0!
1/
10
1(
#2240
0/
00
0(
#2250
b100 7
b1 8
b1 :
1/
10
1(
#2260
0/
00
0(
#2270
b1 4
b10 8
b10 :
1/
10
1(
#2280
0/
00
0(
#2290
b10 4
b11 8
b11 :
1!
1/
10
1(
#2300
0/
00
0(
#2310
b11 4
b100 6
b100 8
b100 :
0!
1/
10
1(
#2320
0/
00
0(
#2330
b100 4
b101 8
b101 :
1/
10
1(
#2340
0/
00
0(
#2350
b101 4
b110 8
b110 :
1!
1/
10
1(
#2360
0/
00
0(
#2370
b110 4
b100100 6
b111 8
b111 :
1/
10
1(
#2380
0/
00
0(
#2390
b111 4
b1100100 6
b101 <
b0 8
b0 :
0!
1/
10
1(
#2400
0/
00
0(
#2410
b1100 -
bx )
bx .
bx 9
b101 7
b0 4
b10 <
b0 ;
1"
1/
10
1(
#2420
0/
00
0(
#2430
b1100100 '
b1100100 1
b1100100 5
0&
1%
b10 7
b11 <
bx ;
0#
0"
1!
1/
10
1(
#2440
0/
00
0(
#2450
1&
b0 6
b0 '
b0 1
b0 5
0%
b100 <
1#
0!
1/
10
1(
#2460
0/
00
0(
#2470
b100 7
b1 8
b1 :
x!
1/
10
1(
#2480
0/
00
0(
#2490
b1 4
b0x 6
b10 8
b10 :
1/
10
1(
#2500
0/
00
0(
#2510
b10 4
b0xx 6
b11 8
b11 :
1/
10
1(
#2520
0/
00
0(
#2530
b11 4
b0xxx 6
b100 8
b100 :
1/
10
1(
#2540
0/
00
0(
#2550
b100 4
b0xxxx 6
b101 8
b101 :
1/
10
1(
#2560
0/
00
0(
#2570
b101 4
b0xxxxx 6
b110 8
b110 :
1/
10
1(
#2580
0/
00
0(
#2590
b110 4
b0xxxxxx 6
b111 8
b111 :
1/
10
1(
#2600
0/
00
0(
#2610
b111 4
b0xxxxxxx 6
b101 <
b0 8
b0 :
1/
10
1(
#2620
0/
00
0(
#2630
b1101 -
b101 7
b0 4
bx 6
b10 <
b0 ;
1"
1/
10
1(
